Metadata-Version: 2.1
Name: ddns-manager
Version: 0.1.3
Summary: Keep your ddns up to date
Home-page: https://github.com/hbontempo-br/ddns-manager
Author: hbontempo-br
Author-email: me@hbontempo.dev
License: MIT
Platform: UNKNOWN
Classifier: License :: OSI Approved :: MIT License
Classifier: Programming Language :: Python
Classifier: Programming Language :: Python :: 3
Requires-Python: >=3.6
Requires-Dist: click (==8.0.1)
Requires-Dist: PyYAML (==5.4.1)
Requires-Dist: requests (==2.25.1)
Requires-Dist: retry (==0.9.2)
